uspto_rejections_kayal_pillay/__init__.py
uspto_rejections_kayal_pillay/uspto_rejections_kayal_pillay.py
uspto_rejections_kayal_pillay-0.1.0.dist-info/LICENSE
uspto_rejections_kayal_pillay-0.1.0.dist-info/WHEEL
uspto_rejections_kayal_pillay-0.1.0.dist-info/METADATA
uspto_rejections_kayal_pillay-0.1.0.dist-info/RECORD
