Metadata-Version: 2.1
Name: uspto-rejections-kayal-pillay
Version: 0.1.0
Summary: Package to interact with the USPTO Rejections API
Home-page: https://github.com/KayalPillay/uspto_rejections_kayal_pillay
License: MIT
Author: Kayal Pillay (mmp2227)
Requires-Python: >=3.9,<4.0
Classifier: License :: OSI Approved :: MIT License
Classifier: Programming Language :: Python :: 3
Classifier: Programming Language :: Python :: 3.9
Classifier: Programming Language :: Python :: 3.10
Project-URL: Documentation, https://uspto-rejections-kayalpillay.readthedocs.io/en/latest/
Project-URL: Repository, https://github.com/KayalPillay/uspto_rejections_kayal_pillay
